portwatch/__init__.py
portwatch/cli.py
portwatch/notifyer.py
portwatch/portconfig_screen.py
portwatch/scaner.py
portwatch/utils.py
portwatch-0.1.2.dist-info/METADATA
portwatch-0.1.2.dist-info/WHEEL
portwatch-0.1.2.dist-info/entry_points.txt
portwatch-0.1.2.dist-info/top_level.txt
portwatch-0.1.2.dist-info/RECORD
