Metadata-Version: 2.4
Name: portwatch
Version: 0.1.2
Summary: A real-time TUI app to monitor, filter, and kill processes using dev ports — with conflict alerts and built-in config UI.
Author-email: Madushanaka Rajapaksha <madushanakarajapakshe999@gmail.com>
License: MIT
Project-URL: Homepage, https://github.com/madushanakarajapakshe999/portwatch
Project-URL: Repository, https://github.com/madushanakarajapakshe999/portwatch
Project-URL: Bug Tracker, https://github.com/madushanakarajapakshe999/portwatch/issues
Project-URL: Documentation, https://github.com/madushanakarajapakshe999/portwatch#readme
Project-URL: Changelog, https://github.com/madushanakarajapakshe999/portwatch/blob/main/CHANGELOG.md
Classifier: Development Status :: 4 - Beta
Classifier: Environment :: Console
Classifier: Environment :: Console :: Curses
Classifier: Intended Audience :: Developers
Classifier: Intended Audience :: System Administrators
Classifier: License :: OSI Approved :: MIT License
Classifier: Operating System :: OS Independent
Classifier: Programming Language :: Python :: 3
Classifier: Programming Language :: Python :: 3.10
Classifier: Programming Language :: Python :: 3.11
Classifier: Programming Language :: Python :: 3.12
Classifier: Topic :: System :: Monitoring
Classifier: Topic :: System :: Networking
Classifier: Topic :: Utilities
Requires-Python: >=3.10
Requires-Dist: textual>=0.49.0
Requires-Dist: psutil>=5.9.0
Requires-Dist: plyer>=2.1.0
Requires-Dist: pyyaml>=6.0
Requires-Dist: rich>=13.0.0
Provides-Extra: dev
Requires-Dist: black; extra == "dev"
Requires-Dist: ruff; extra == "dev"
Requires-Dist: pytest; extra == "dev"
Requires-Dist: textual-dev; extra == "dev"
Requires-Dist: win10toast; extra == "dev"
Requires-Dist: pywin32; extra == "dev"
Requires-Dist: pyyaml; extra == "dev"
